{"index": {"limited": [6], "historiographic": [9], "dynamic": [7], "disability": [4, 6], "the-iudhies-an-international-undergraduate-digital-humanities-prize": [7], "how-did-they-make-adams-timeline": [7], "under": [6], "teaching": [7], "worth": [2], "collaborate": [9, 2, 5], "video-chat": [2], "replication": [5], "every": [6], "updates": [1], "school": [7], "skills": [9, 5], "conceive": [7], "solution": [2], "convenience": [11], "enhance": [7], "reinvent": [7], "charter": [2], "force": [2], "direct": [6, 9, 2, 7], "surrounding": [7], "second": [14, 2], "rigorous": [6], "blue": [2], "nullism": [1], "religious": [6], "workflow": [1], "scrolling": [8], "above": [1, 7], "conduct": [4, 6, 9], "net": [2], "ever": [4], "wondermark": [2], "maintains": [13], "never": [2], "here": [2, 7, 4, 6], "represented": [7], "balance": [14], "items": [6, 7], "leaves": [2], "changed": [9], "credit": [9, 14, 6], "special-students": [14], "jekyll-now": [12], "suitable": [7], "midway": [5], "appropriately": [7], "divide": [7], "mobility": [6], "44241": [14], "psychological": [6], "counts": [7], "total": [7], "landscape": [5], "would": [7, 2, 6], "call": [7, 5], "strike": [13], "25th": [14], "assessment": [2, 9, 11, 6, 7], "tell": [7, 2, 6], "successful": [7], "naive": [4], "aware": [7], "disruption": [4], "excellent": [13, 7], "hold": [2, 14], "startbootstrap-grayscale-1": [7], "must": [14, 7, 2, 6], "word": [5, 7], "rights": [6], "work": [7, 2, 6, 5, 13, 9, 14, 1, 4], "install": [2, 13], "concepts": [6], "example": [2], "give": [2, 9, 5, 13], "cited": [7], "motivated": [9], "locative": [7], "want": [2, 9], "keep": [2, 1, 7], "end": [13, 2, 4, 5, 6, 7, 9, 14], "machine": [13, 11, 1], "how": [2, 7, 5, 9, 14, 1, 4, 11, 13], "cname": [1], "interview": [6], "registrar": [14], "truthful": [7], "description": [2], "long-form": [7], "typed": [5], "after": [14, 2, 4, 6, 7], "wrong": [2, 9, 13, 7], "meaningful": [9, 5], "effective": [7], "bootstrap": [12], "residential-school-online-response": [7], "maintain": [4], "suggest": [7, 2], "order": [6], "office": [1, 2, 14], "over": [5, 7], "expects": [9], "viewform": [15], "london": [2], "before": [2, 6, 7], "img": [11, 5, 6], "writing": [9, 7, 1], "better": [7], "406": [1], "production": [7], "compelling": [7, 9], "public-facing": [2], "weeks": [6, 7], "easier": [5], "then": [2, 1, 7, 9, 5, 13], "them": [7, 1, 2, 5], "combination": [7], "safe": [2, 6, 7], "intimidation": [4], "break": [9], "they": [7, 2, 6, 9, 5], "schools": [7], "yourself": [2, 7, 9, 4, 13], "programminghistorian": [2], "alex": [12], "1k62": [2], "absolve": [2], "each": [2, 7, 5, 4], "went": [7], "side": [1, 2], "mean": [4, 5, 13, 7], "financial": [14], "series": [5], "principles": [9, 2, 7], "commons": [6], "used": [1, 6], "hosted": [13], "substantially": [6], "laboratory": [13, 6], "extract": [7], "sounds": [9], "crucial": [7], "encourage": [2, 13, 7], "daniel": [7], "reader": [7], "got": [9, 2, 7], "img-open-access": [11], "associate": [1, 6], "hang": [7], "free": [13, 6, 9, 11], "standard": [2, 6], "sensory": [6], "disputes": [6], "created": [12, 7], "renew": [13], "webspace": [13], "organize": [2], "grade": [5, 6], "primary": [7], "pratice": [7], "another": [6, 5, 7], "toy": [5], "similarly": [1], "engagement": [2], "historian": [9, 2], "needed": [2], "master": [7, 2, 13], "too": [1, 2, 4, 13], "toc": [1, 2, 5, 6, 7, 9, 13, 14], "yourusername": [12], "tool": [2, 7, 9], "begins": [5], "past": [7, 1, 5], "target": [11], "roles": [6], "likely": [7], "project": [7, 2, 6, 1, 5], "classes": [13], "historical": [5, 9, 7], "youre": [2, 7], "sees": [5], "caleb": [2], "mine": [2], "talking": [7], "manner": [9, 7], "corny": [4], "adhd": [6], "seem": [7], "realm": [5], "img-crafting": [11], "materials": [5, 2], "responsibly": [6], "paradata": [2, 7, 6], "letter": [6], "exercises": [2, 13, 5, 6, 7], "assessed": [9, 2], "marie": [1], "peers": [2, 4], "don": [5], "observation": [5], "medical": [6], "img-robot": [11], "points": [2, 7, 5], "tech": [7], "dot": [14, 1], "incorporate": [5], "selected": [6], "random": [2], "visualisation": [2], "participate": [2], "lessons": [2], "finally": [13], "consciousness": [5, 7], "implementation": [2], "theme": [12], "folks": [2, 13], "rice": [2], "mixture": [7], "designing": [7], "stop": [4], "psychiatric": [6], "despite": [7], "geekfeminisms": [4], "johanna": [7], "fields": [5], "method": [5], "theory-laden": [9], "release": [6], "187297": [11], "reference": [1, 13, 6], "result": [5, 7], "fail": [7, 5], "best": [7, 9, 4, 2, 5], "subject": [6], "inappropriate": [4], "wikipedia": [5], "808": [8], "wrangling": [9], "approach": [7], "preserve": [6], "reddit": [7], "terms": [7], "nature": [7], "however": [2, 14], "harvard": [7], "behaviour": [4], "against": [5], "participating": [14], "receives": [6], "requests": [6], "com": [13, 2, 1, 12, 7, 9, 3, 8, 10, 11, 15, 16, 17], "workplans": [7], "height": [9, 1, 3, 7, 8, 10, 12, 15, 16, 17], "game-theoretic": [4], "pregnancy": [6], "trust": [7], "speak": [7], "chrome": [13], "three": [7], "been": [6, 5, 7], "much": [7, 2, 5], "replicate": [5], "tutorials": [1], "col-sm-4": [11], "col-sm-6": [11], "website": [2, 11, 12, 13, 6], "eastern": [2], "craft": [5, 2, 14, 7], "zijlstra": [1], "affirm": [6], "employ": [9], "contemplates": [5], "menton": [6], "voice": [9], "study": [6], "thursdays": [2], "pre-cooked": [12], "cant": [2], "grown": [2], "academically": [14], "perform": [4], "things": [13, 2, 7, 9, 5], "make": [7, 2, 13, 9, 5], "big": [9, 2], "wheel": [7], "meets": [2], "published": [14, 6], "middle-aged": [2], "hand": [1, 2], "portal": [14], "potentials": [9, 13], "thoughts": [2], "cycle": [5], "darned": [7], "hypothes": [13], "failing": [6, 5], "disseminated": [2], "academic": [6, 14, 9, 4, 7], "contact": [14, 6, 9, 4], "yours": [13], "wider": [9], "left": [5, 7], "graded": [2, 7], "just": [7, 5, 2, 4], "true": [8, 15], "laptop": [1], "grades": [6, 2], "identify": [9], "human": [6], "yes": [5, 7], "previous": [7], "visualization": [5, 7], "instance": [7, 2], "had": [2, 4], "easy": [9, 4], "bna": [7], "has": [6, 7, 1, 9, 5], "grounding": [9], "possible": [2, 5, 6, 15], "unique": [5], "desire": [2], "getting-started": [11], "issue-1": [7], "specific": [6], "steps": [9, 7], "lapses": [7], "security": [7], "www": [2, 1, 7, 9, 3, 10, 11, 12, 13, 14, 16, 17], "right": [2, 4, 6], "dean": [6], "crowd": [2], "people": [7, 5, 2], "somehow": [7], "dead": [7], "jennifer": [7], "harassment": [6], "confusing": [13], "shapes": [5], "for": [2, 7, 6, 14, 9, 13, 1, 11, 12, 4, 5], "grading": [7, 2], "comments": [4], "creative": [6, 2], "everything": [7, 2, 1, 12, 5], "asking": [7], "denied": [14], "420": [3, 12], "participation": [14], "repository": [2, 12, 1, 7], "payment": [14], "provocations": [7], "losing": [2], "post": [2, 7], "permitted": [14], "proceed": [14], "newspapers": [7], "ensure": [6], "horizon": [5], "efforts": [7], "dilemma": [4], "johns": [7], "prisoners": [4], "lies": [5], "support": [4, 14, 7], "initial": [13], "class": [11, 6, 7, 13, 4, 5, 9], "width": [9, 1, 3, 7, 8, 10, 12, 15, 16, 17], "accordingly": [7], "wordpress": [1], "way": [2, 1, 9, 5, 7], "was": [7, 2, 4, 5], "happy": [1], "fork": [1, 12, 13], "medium": [7], "form": [7], "sundry": [6], "landing": [12], "cumail": [13], "failure": [2], "btn-primary": [11], "sustained": [4], "evaluative": [2], "portions": [6], "type": [9], "attached": [14], "until": [2, 6], "submitting": [6], "explicated": [7], "bestpractice": [7], "computing": [2], "textbook": [9], "evidence": [7, 2], "exist": [6], "check": [1, 14], "physical": [6], "techy": [5], "setting": [13, 12, 16, 2, 11], "digital": [5, 2, 9, 13, 7, 11, 1, 14], "test": [6], "welcome": [2, 7], "convincing": [9], "fell": [2], "frameborder": [9, 1, 3, 7, 8, 10, 12, 15, 16, 17], "modules": [7, 2, 9], "together": [7, 9, 2], "time": [7, 2, 5], "push": [9, 2, 5, 7], "serious": [6], "stick": [9], "real-time": [9], "themes": [7], "graphing": [9], "chair": [5], "epistemic": [9], "row": [11], "environment": [4, 6], "charge": [7], "marks": [6], "choice": [9, 7], "fees": [14], "join": [11], "exact": [2], "cool": [1], "glyphicon": [11], "level": [2, 5], "did": [7], "turns": [1], "posts": [1, 5, 6], "standards": [4], "leave": [2, 7], "quick": [13], "div": [11], "prevent": [6], "findings": [9, 6], "dealing": [4], "pmc": [6], "appear": [9], "heres": [2, 12, 7], "paragraph": [6], "template": [2], "one-page": [6], "shared": [2], "elses": [2], "alone": [7], "along": [5], "appears": [5], "change": [5], "sending": [7], "enroll": [14], "canadian": [14], "accomplished": [14], "reclaim": [13], "regardless": [14, 6], "raise": [7], "merely": [7], "thumbnail": [11], "working": [9, 4, 7, 2, 5], "listenable": [7], "msu": [7], "visit": [6], "crowdsourcing": [7], "text-muted": [11], "live": [2, 6], "explicitly": [2], "88x31": [6], "https": [13, 7, 1, 12, 2, 9, 3, 6, 10, 11, 14, 15, 16, 17], "criteria": [14, 7], "scope": [6], "theoretical": [9, 5], "heritagecrowd": [7], "sharing": [1, 6], "outputs": [7], "apparent": [2], "envelope": [7], "refrain": [4], "visual": [7, 9], "everywhere": [1], "effort": [7], "hardest": [7], "2015-08-10-do-i-own-my-domain-if-you-grade-it": [2], "values": [7], "can": [2, 5, 13, 7, 9, 6, 1, 12, 14, 4], "iframe": [9, 1, 3, 7, 8, 10, 12, 15, 16, 17], "following": [2, 4, 7], "making": [8, 9, 4], "arrive": [2], "dedicated": [7], "figure": [9], "december": [11], "sense": [4, 7], "topic": [7, 5, 6], "heard": [4], "occur": [2], "productive": [7, 2, 5], "requirements": [14], "winter": [14, 6, 11], "discussion": [2], "means": [2, 6], "write": [2, 7, 1, 9, 6], "map": [7], "product": [7, 2], "designer": [1], "explores": [5], "may": [2, 6, 9], "2014-09-19-1062sea": [2], "sustainability": [2], "produce": [7], "designed": [2], "divy": [2], "date": [6, 14, 7], "such": [2, 12, 6], "data": [9, 7, 5, 6], "annotation": [13], "man": [2, 5], "classroom": [7], "noun": [11, 1], "outline": [14, 6], "whenever": [12], "maybe": [2, 5, 7], "explicit": [2], "talk": [5, 7, 2, 13], "refund": [14], "acts": [9], "indeed": [14, 7], "in-class": [6, 7], "years": [7], "course": [14, 6, 9, 7, 13, 2, 5, 1, 4, 11], "still": [14, 7], "tendency": [9], "group": [2], "acknowledge": [6, 7], "interesting": [13, 7], "forms": [15], "plagiarized": [6], "puzzle": [7], "non": [7], "weekly-template": [2, 13], "conversations": [4, 13], "introduce": [2], "answer": [9, 7], "mutliple": [9], "not": [2, 7, 5, 6, 14, 4, 9, 13], "now": [9, 7], "discuss": [2], "term": [14, 6, 5, 7], "name": [2], "january": [14], "repositories": [13], "entirely": [6], "domain": [1, 2, 13, 7], "challenged": [2], "authenticity": [2], "happen": [2], "hand-held": [7], "living": [13], "two-fold": [2], "space": [2, 7, 12, 13, 5], "interference": [6], "looking": [2, 7], "seriously": [7], "investigation": [6], "internet": [2, 5], "receiving": [4, 14], "shows": [7, 4], "quite": [13], "unwanted": [4], "org": [7, 2, 6, 4], "accommodation": [6], "card": [7], "grist": [5], "language": [14, 6, 7], "thing": [1, 7], "place": [2, 13], "massive": [9], "think": [7, 2, 13], "riffing": [4], "first": [7, 6, 2, 9], "origin": [4], "galarza": [12], "crib": [9], "one": [5, 6, 7, 2], "submit": [6, 2, 14, 7], "directly": [6], "carry": [6], "message": [6, 9, 2, 7], "open": [14, 16, 9, 2, 7, 1, 5, 11], "millions": [9], "given": [7], "necessarily": [6], "anyone": [2], "finding": [9], "white": [2], "cite": [7], "speaking": [2], "exploring": [7], "mining": [9], "mostly": [9], "that": [7, 2, 5, 13, 6, 9, 1, 4, 12, 14], "shawn": [1, 14], "accurately": [7], "self-directed": [9], "github": [12, 10, 16, 7, 2, 13, 1], "copy": [1, 2, 13], "representing": [5], "than": [6, 7, 2, 5], "png": [11, 2, 5, 6], "glyphicon-ok": [11], "require": [6], "future": [13], "were": [7, 2, 4], "accessed": [14], "outcome": [9], "browser": [13], "pre": [9], "documentation": [2], "stylings": [7], "argument": [7, 9, 5], "say": [5, 2], "any": [6, 2, 14, 5, 7], "astonishingly": [5], "exploratory": [7], "efficient": [9], "ideas": [6, 7], "1qcbpndyjkletohcsxle4sxvncjmtt3ybcbl3twvu3dg": [15], "note": [14, 9, 2, 13, 7], "potential": [14], "take": [7, 2, 4, 6, 9, 13], "online": [9, 13, 14, 2, 4, 5, 6, 7, 12], "channel": [7, 9, 2], "handing": [6], "sure": [7, 9, 5], "multiple": [9], "trace": [2], "normal": [14], "track": [2], "enter": [13], "fails": [2], "gitbook": [11], "america": [13], "pages": [10, 6], "later": [6], "implications": [7], "archaeology": [1, 2], "raquo": [11], "professional": [12], "typically": [2], "precise": [2], "show": [2, 5], "recipe": [5], "spaces": [13], "corner": [5], "ottawagunner": [7], "clarifications": [6], "title": [7], "breadcrumbs": [2], "enough": [1, 7], "short": [6, 7], "analytic": [7], "only": [14, 2, 6, 7], "going": [9, 2, 13, 5, 7], "equipped": [5], "xo7dqi": [17], "awareness": [9], "get": [2, 7, 11, 5], "repo": [8], "cannot": [14, 6], "handknittedlaptop": [5], "secondary": [7], "regarding": [14], "frustrated": [9], "summary": [6], "conferencing": [9], "where": [2, 9, 13, 5, 7], "ignored": [7], "calendar": [14, 13], "exam": [6], "suspects": [6], "registering": [14], "ways": [2, 5], "review": [14, 6], "hist": [14], "outside": [11, 7], "between": [5, 2], "reading": [9, 2], "across": [9], "wouldve": [7], "screen": [4], "othertimes": [9], "come": [5, 7, 2], "dates": [6, 9, 14], "fit": [13], "many": [7, 2, 12], "quiet": [5], "expression": [6], "comes": [5, 7], "-sauorqgbh0": [9], "key": [7], "overview": [2], "period": [7], "learning": [9, 2, 6, 14, 5], "approval": [14, 6], "cancel": [13], "27853": [11], "considering": [7], "howard": [7], "ucla": [7], "breath": [5], "workshop": [13], "reflective": [2], "500": [15], "mhbeals": [7], "appleford": [7], "enable": [13, 5, 7], "hasblm-qz3a": [1, 9], "readings": [9, 2, 7], "photos": [1], "hashtag": [13], "craftiness": [5], "careful": [5], "those": [9, 14, 7, 2], "case": [7], "om-52iqdrmw": [3], "these": [2, 7, 1, 13, 5, 6, 14], "hands-on": [5], "invoking": [7], "policies": [6], "ive": [1], "orientation": [4], "culearn": [9], "according": [9, 7], "someone": [2, 6, 5, 7, 9, 12], "somebody": [7], "different": [12, 5, 7], "develop": [9], "etc": [6, 7], "insofar": [2], "same": [9, 12, 5, 6], "html": [10, 11, 2, 9, 6, 1, 13], "arguments": [7], "document": [7, 2], "breakdown": [2], "extended": [6], "screenshot": [1], "director": [13], "changing": [5], "ecampusontario": [14], "threaded": [13], "eureka": [5], "without": [6, 5], "solve": [2], "workplan": [7], "very": [7], "model": [9, 5], "scholarship": [7], "being": [9, 4, 5, 14, 7], "when": [7, 2, 5, 6, 9, 13, 1, 14], "guided": [5], "underline": [7], "captured": [7], "provocation": [7], "grounded": [7], "thinking": [2, 7], "except": [2], "desktop": [13], "blog": [1, 12, 6, 7], "interested": [2, 14, 7], "watchable": [7], "blob": [7, 2, 13], "scheduled": [6], "around": [7, 9], "read": [2], "offence": [6], "using": [6, 1, 2, 7, 9, 12], "disappointed": [2], "christina": [7], "conducts": [6], "facing": [2], "audience": [7], "either": [7], "fully": [4], "served": [12], "barryclark": [12], "specified": [6], "duration": [7], "questionnaire": [15, 9], "divine": [5], "matching": [9], "open-notebook-history": [2], "provided": [2], "mood": [7], "micro": [7], "colonial": [7], "critical": [9, 7], "deficit": [6], "communicate": [9], "tuition": [14], "devising": [7], "exciting": [5], "src": [11, 5, 9, 1, 3, 6, 7, 8, 10, 12, 13, 15, 16, 17], "crafting": [5, 11, 9], "package": [1], "disabilities": [6], "violence": [4], "discussed": [2, 13], "generated": [1], "stand": [5], "youve": [2, 5, 7], "road": [5], "quietly": [5], "communication": [4], "youd": [7], "annotate": [13], "odonell": [7], "your": [7, 13, 2, 6, 5, 9, 11, 4, 12, 1], "shaker-style": [5], "her": [7], "aren": [9], "strictly": [2], "there": [2, 5, 14, 7, 13, 4, 11, 12], "styling": [7], "deadlines": [14], "start": [7, 13, 5], "lot": [7, 13], "chats": [2, 9, 7], "complete": [14, 9, 6, 7], "verbatim": [6], "promote": [6], "with": [16, 2, 6, 7, 14, 9, 1, 5, 13, 4], "1025": [14], "pull": [8], "datasets": [7], "arranged": [2], "embedded": [15], "embed": [9, 1, 3, 7, 8, 10, 12, 16, 17], "agree": [5], "hist3907o": [11, 13, 14], "strongly": [7], "videos": [7, 13, 6], "gratuitous": [4], "certain": [2], "citation": [6], "general": [14], "examine": [5], "file": [1], "fill": [15], "unwelcome": [4], "middlesex": [7], "mandated": [9], "field": [9, 13], "glyphicon-download": [11], "evenings": [2], "you": [2, 7, 13, 9, 5, 14, 4, 6, 12, 1, 11], "collaborative": [2], "separate": [7], "students": [14, 6, 7], "miriam": [7], "includes": [14], "important": [7, 2, 5], "suited": [7], "equitable": [2], "482": [8], "building": [2, 7, 5], "calls": [2], "coljnqhtkq": [8], "websites": [1, 9, 6, 7], "posners": [7], "startbootstrap": [12], "adam": [9], "signalling": [2], "oral": [7], "original": [2, 6, 7], "all": [7, 2, 14, 4, 6, 1, 5, 13], "ali": [1], "debris": [7], "deadline": [14], "fairness": [6], "follow": [7], "alt": [11, 6], "decisions": [2], "reasoning": [2], "icons": [1], "presentation": [7], "sound": [4, 5], "appointment": [2], "far": [5, 9], "fall": [6], "leads": [7], "forking": [8, 2], "accompanying": [7], "evaluation": [9, 6], "list": [13], "plotting": [9], "crymble": [9], "helpful-things": [2, 13], "penalties": [6], "sync": [1], "perspectives": [9], "knitted": [1], "disability-related": [6], "design": [7], "further": [2], "mill": [5], "what": [2, 7, 5, 9, 13, 14, 6], "stood": [11], "sonification": [5], "section": [14, 2, 7], "version": [1, 11, 14], "sshrc": [9], "learned": [2], "screencast-o-matic": [8, 13], "public": [2, 7, 9, 13, 5], "contrast": [2, 6], "wcm1": [2], "hours": [7, 1, 2], "scissorsandpaste": [7], "dh101": [7], "search": [1, 13, 9], "ahead": [4], "allows": [7, 13], "prior": [6], "amount": [2], "base": [12], "social": [4, 7], "options": [12, 14], "via": [7, 9, 6, 1, 2], "requiring": [6, 14], "studentaccounts": [14], "ask": [2, 7], "href": [11, 6], "analyzing": [9], "aimed": [2], "select": [2, 7], "eye": [9, 7], "takes": [12], "objectives": [2], "contains": [7], "two": [2, 6, 7], "paraphrased": [6], "minor": [2], "more": [2, 5, 6, 7, 11, 1, 14], "flat": [7], "admissions": [14], "basically": [4], "particular": [2, 7], "known": [6], "mounted": [7], "producing": [5], "keeping": [7], "plagiarism": [6], "debates": [7], "hour": [7], "science": [5, 2], "installing": [13], "remain": [1], "arrangements": [2, 6], "sent": [6], "den": [1], "learn": [11, 7, 1, 2, 9], "history": [5, 2, 7, 9, 13, 11, 14], "compare": [9], "pushes": [5], "stated": [14, 7], "beals": [7], "share": [2, 5, 6, 7], "states": [6], "minimum": [2, 6], "numbers": [7], "arise": [5], "axis": [5], "information": [14, 2, 6, 7], "needs": [6, 4, 5], "interconnect": [13], "jafri": [1], "rather": [7, 1, 2, 9, 5], "comfort": [2], "maps": [7], "csv": [7], "communicating": [9], "advice": [4], "mapping": [9, 7], "reflect": [7], "off-load": [5], "faculty": [6], "marginheight": [15], "undergrads": [14], "imagery": [4], "register": [14, 6], "responsibility": [9, 6], "marginwidth": [15], "media": [9, 11, 5], "crafty": [5], "ryanpickering": [7], "help": [3, 2, 7, 5, 6], "essence": [2], "itd": [7], "soon": [2, 6, 15], "through": [13, 5, 2, 14, 4, 6, 7, 9, 12], "committed": [9], "its": [7, 5, 2, 13, 6], "style": [7, 5, 6], "microscoft": [1], "blurring": [5], "actually": [7, 4], "might": [4, 2, 6, 7, 9, 13], "3907o": [14], "good": [9, 2, 5, 7], "return": [2], "instructions": [2], "always": [1, 2, 9], "presented": [7], "courses": [14, 7, 2, 6], "uploads": [11, 5], "experiencing": [13], "found": [9, 2, 7], "button": [2], "week": [2, 6, 7], "everyone": [2, 13], "broeck": [1], "hard": [5], "idea": [2, 1], "expect": [2, 5], "beyond": [2, 7], "event": [5], "really": [2, 4], "ftp": [1], "research": [2, 9, 7, 1, 4, 5, 6, 11], "participants": [11], "padding-right": [5], "offline": [13], "issue": [2, 7], "occurs": [6], "housed": [2], "electricarchaeo": [1], "like": [9, 1, 5, 6, 7, 13], "experimenting": [5], "daea": [7], "members": [6], "put": [9, 2, 4, 13, 7], "teach": [9], "guiliano": [7], "threat": [6], "neglected": [7], "major": [7], "dont": [7, 2], "feel": [13, 5, 7], "number": [7, 11, 13], "explored": [7], "done": [2, 7], "blank": [11], "story": [7, 9, 6], "leverage": [11], "pandoc": [1], "introduction": [17, 2], "least": [2, 7], "statement": [6], "creativecommons": [6], "essays": [7], "listed": [14], "option": [14, 11], "relationship": [2], "checklist": [2], "part": [2, 13, 6, 7], "consult": [14], "believe": [2], "kind": [4, 13, 7], "critically": [5], "aims": [2], "determined": [6], "interactive": [7], "outstanding": [14], "disenchanted": [1], "the-unessay": [7], "boilerplate": [6], "psuedonymn": [2], "depending": [7], "humdata": [7], "also": [2, 13, 1, 6, 7, 14], "costs": [13], "build": [7], "ancillary": [7], "sharonhoward": [7], "transparent": [9], "towards": [9], "components": [7], "reckon": [7], "most": [7, 9, 13, 5], "plan": [7, 9, 6], "dhcommons": [7], "services": [6], "creating-an-omeka-exhibit": [2], "approved": [6], "clear": [7], "sometimes": [5, 7, 2], "clean": [9], "velocity": [16], "obligations": [6], "accommodations": [6, 14], "cdt": [7], "stumped": [2], "session": [2], "carefully": [5, 6], "tuesdays": [2], "find": [9, 5, 7, 2, 6], "copyright": [6], "writes": [9], "penalty": [6], "increasingly": [9], "experiment": [13], "annotations": [13], "equity": [6], "his": [2, 7], "goes": [12, 7], "permission": [6], "compiled": [7], "rutmer": [1], "international": [6], "during": [6, 2], "him": [5], "deductive": [2], "continuum": [5], "progressive": [9], "withdrawal": [14, 6], "wrote": [7], "set": [2, 13, 9, 12], "art": [5], "unpublished": [6], "315": [9, 1, 3, 7, 10, 12, 16, 17], "see": [7, 2, 13, 1, 6, 9], "individual": [1, 14], "are": [7, 2, 9, 6, 13, 4, 14, 1, 5, 11, 12], "craftingdigitalhistory": [13, 2, 1, 7, 9, 11], "skill": [5], "deploying": [1], "practice": [5, 7], "visualize": [9, 5], "threats": [4], "unacknowledged": [2], "ftfh-hrjcys": [12], "please": [6, 9, 14, 4, 7, 13, 15], "libraries": [7], "misjudge": [4], "various": [9, 2, 7], "probably": [9], "weekly": [2], "conditions": [6], "knowing": [5], "attention": [4, 5, 6], "ecampus": [14], "succeed": [9, 5], "distinguish": [4], "both": [13, 9, 4], "useable": [9], "last": [14, 6], "license": [6], "londoncharter": [2], "context": [5, 7], "pdf": [11], "procedural": [9], "whole": [7, 6], "markdown": [1], "point": [1, 5, 6], "community": [2, 6, 5, 7, 9, 13], "simply": [9, 14, 7], "described": [7], "hiatus": [2], "create": [2, 13, 7], "due": [6, 9], "strategy": [2], "whom": [2, 4], "citations": [6], "mind": [5], "transferring": [7], "great": [5, 13], "else": [6, 1, 5, 7], "understand": [13], "1867": [7], "instructor": [6, 14], "look": [7, 4, 13], "requirementsandprocedures": [14], "receive": [13], "while": [5, 6], "theres": [2, 4], "real": [4, 2], "hoping": [5], "hyperactivity": [6], "jpg": [5], "reads": [1], "ready": [11], "rules": [14], "pykwiki": [1], "futzing": [1], "advise": [9], "literature": [7, 9], "rhetorics": [9], "assignment": [6], "alert": [7], "levels": [2], "uses": [2, 7], "built": [9], "edsurge": [2], "mobi": [11], "lib": [7], "database": [7], "spent": [9], "analysis": [7], "person": [4, 2], "withdraw": [14, 6], "entry": [1], "spend": [7], "know": [2, 5, 7, 14], "one-year": [13], "760": [15], "xtina-r": [7], "shape": [9], "questions": [5, 14, 7, 9], "world": [9, 14], "useful": [9, 13, 7], "loading": [15], "conclusions": [7], "admission": [14], "source": [2, 6, 4, 5, 7], "location": [9], "march": [6], "format": [1, 7], "evaluate": [5], "showing": [9, 14], "matters": [6], "bit": [7], "projects": [7, 14], "formal": [2, 6], "submission": [6], "bvmiuhmyd6u": [16], "signal": [2], "holes": [9], "ignore": [5], "communications": [13], "indication": [2], "disorder": [6], "google": [7, 1, 5, 9, 13, 15], "methods": [2, 7], "senate": [6], "some": [7, 2, 4, 13, 14], "back": [1, 2], "bounce": [7], "understood": [2], "trends": [7], "examples": [7], "katemonkey": [1], "electric": [1, 2], "manageproject": [7], "scale": [6], "per": [7, 2], "religion": [4], "prof": [1], "run": [1, 5, 7], "roomname": [9], "step": [14, 7], "interpretative": [2], "graft": [5], "anything": [2], "by-nc-sa": [6], "allowfullscreen": [9, 1, 3, 7, 8, 10, 12, 16, 17], "genre": [7], "seeing": [13], "into": [2, 1, 5, 7, 9, 12, 13, 14], "within": [9, 7], "gh-pages": [1], "nothing": [2], "appropriate": [7, 9, 4, 6], "self-harm": [4], "primarily": [9], "screen-cast-o-matic": [13], "ontario": [14], "span": [11, 7], "extremely": [7], "question": [9, 2, 7], "handles": [13], "long": [14, 7], "syllabus": [9, 11], "analyze": [9, 5], "sections": [2], "files": [1, 2, 7], "elsewhere": [14], "registered": [14, 1, 6], "memory": [5], "link": [2, 6, 13], "line": [1], "posted": [2], "directed": [14], "stalking": [4], "highlight": [13], "called": [2, 12, 7], "powered": [1], "associated": [9, 6], "shortcuts": [7], "doesn": [7], "images": [1, 4], "chat": [2], "hapened": [7], "graham": [14, 1, 6, 9], "defines": [6], "codeofconduct": [9, 6], "humanities": [1, 13], "amounts": [9], "cohesive": [2], "scrape": [9], "application": [14], "one-on-one": [2, 4], "revision": [6], "ecosystem": [13], "beatiful": [5], "problems": [9], "regulations": [14, 6, 9], "meaning": [7], "graphically": [7], "posters": [7], "structure": [9], "feasible": [6], "electricarchaeology": [2, 7, 1], "required": [6], "resolving": [6], "geekfeminism": [4], "presenting": [6], "narrative": [2, 7], "requires": [9, 5], "once": [2, 9, 1, 6], "essay": [6], "code": [4, 13, 7, 9, 6], "results": [1, 9], "existing": [7], "infographic": [7], "edu": [2, 7], "simon": [7], "send": [9, 2, 7], "suits": [7], "helps": [7], "visualizing": [9], "include": [6, 7], "resources": [1, 9, 7], "wishes": [2], "facebook": [2], "continued": [4], "btn-md": [11], "gender": [4], "notes": [2], "ryan": [7], "try": [2, 5], "assignments": [9, 14], "skipped": [7], "race": [4], "configurations": [5], "limitations": [9], "visuals": [7], "licensed": [6], "video": [17, 9, 13, 2, 7, 12], "licenses": [6], "click": [13], "index": [13], "developed": [7], "giving": [9], "practices": [9], "access": [14, 9, 2, 5, 11, 13], "f5szytcvhh4": [7], "exercise": [3, 2], "degree": [7, 14], "pushing": [2], "explore": [7], "let": [2, 9], "others": [9, 7, 6], "consideration": [7], "implicit": [2], "convert": [1], "technical": [5], "larger": [5, 7], "resulting": [5], "makes": [5, 7], "involves": [5], "thats": [2, 7, 5], "apple": [1], "win": [4], "app": [7], "manage": [7], "private": [2, 13, 4, 7], "outcomes": [9, 2], "apply": [14], "tools": [9, 7, 1], "unessay": [7], "manipulate": [9], "standing": [6], "use": [7, 2, 1, 6, 9, 13], "fee": [14], "from": [2, 7, 1, 14, 4, 5, 6, 9, 11], "odonnell": [7], "readable": [1, 7], "next": [2], "doubt": [2], "examination": [6], "face-to-face": [2], "themselves": [9], "formally": [6], "mcdaniel": [2], "becomes": [5], "salvaged": [2], "account": [13, 14], "midterm": [6], "this": [7, 2, 13, 6, 1, 9, 5, 4, 11, 14, 15], "challenge": [2], "text-primary": [11], "uleth": [7], "reproduce": [7], "assumptions": [9], "meet": [14, 2, 6], "didnt": [5, 7], "control": [1, 5], "how-i-lost-the-crowd-a-tale-of-sorrow-and-hope": [2, 7], "process": [14], "lock": [1], "pieces": [2, 11, 5, 13], "high": [7, 4], "tag": [7], "something": [2, 12, 13, 7], "tab": [1], "613-520-6608": [6], "six": [2], "arrangement": [1], "responsibilities": [6], "instead": [1, 6], "tied": [13], "finalproject": [2, 6, 7], "preferred": [9], "fits": [5], "realized": [7], "robot": [1, 11], "element": [7], "honestly": [7], "agenda": [2], "quotations": [6], "classs": [6], "insight": [5], "report": [6], "snafus": [7], "btn-lg": [11], "notebooks": [7], "blogging": [2], "willing": [5, 9], "choose": [13], "visualisation-based": [2], "2015": [11, 7], "13480": [11], "2016": [11, 14, 6], "2013": [7], "2012": [2, 7], "flex": [14], "greater": [5], "python": [1], "docs": [15], "dan": [13], "material": [6, 9, 7], "registrars": [14], "documented": [6, 7], "kindness": [4], "day": [2, 6, 14], "eslr": [14], "february": [14], "mastery": [7], "university": [14, 6], "truth": [5], "reproducing": [4, 6], "illuminate": [7], "doing": [2, 7, 13], "related": [4], "static": [1], "cpanel": [1], "our": [2, 7, 13, 5, 9, 4, 11], "sexual": [4], "special": [14, 6], "out": [7, 2, 9, 4, 5, 6, 15], "category": [2], "matt": [7], "acknowledgment": [6], "mediated": [4], "rel": [6], "supports": [7], "interactions": [4], "activity": [7], "promptly": [6], "analytical": [2, 7], "approaches": [7], "interaction": [4], "could": [2, 7, 5, 6], "code-of-conduct": [4], "times": [2, 5], "conversation": [9], "length": [7], "notebook": [16, 2, 7, 1], "5665916936": [1], "workbook": [2, 13, 9, 11, 7], "distracted": [7], "reflexive": [9], "xvdf": [17], "digitizing": [9], "pywkiki": [1], "sharon": [7], "management": [9, 7], "publication": [4], "privacy": [7], "detailing": [6], "border-width": [6], "their": [2, 14, 5, 6, 7], "typd": [13], "perfectly": [5], "final": [7, 6, 2], "exhorts": [7], "completed": [14], "updating": [2], "remember": [7], "slack": [2, 7, 9, 13, 6], "isolation": [2], "pointers": [1], "youtube": [9, 1, 3, 7, 10, 12, 16, 17], "submitted": [6, 7], "exhibit": [2, 6], "cohen": [13], "correspond": [7], "have": [7, 2, 14, 6, 4, 13], "need": [7, 5, 6, 13, 1, 2, 9, 11], "text-decoration": [7], "documents": [9], "drucker": [7], "able": [9, 5], "walkthroughs": [7], "concerns": [7], "which": [7, 2, 6, 13, 1, 5, 9, 12], "techniques": [7, 5], "lectures": [7], "unless": [7], "on-campus": [14], "centre": [6], "collaboration": [6], "who": [2, 14, 7, 13, 5], "but": [5, 7, 2, 13, 4, 9, 1, 6], "why": [7, 2, 11], "epub": [11], "url": [2, 7], "request": [8, 4, 14, 6], "face": [2, 9], "fact": [2], "selection": [7], "devdh": [7], "visualizes": [7], "chances": [7], "text": [1, 13, 7], "agreed": [6], "teisap": [7], "bring": [5], "planning": [7], "trivial": [6], "zvejle8qtoi": [10], "trying": [7, 2], "based": [2], "knowledge": [2], "sparks": [2], "cache": [1], "should": [2, 14, 7, 5, 6, 13], "5px": [5], "thousands": [9], "move": [13, 5], "watching": [2], "self-disciplined": [9], "procedures": [6], "melodee": [7], "numerous": [9], "undergrad": [14], "stuff": [9], "avoidable": [7], "contain": [2], "including": [7, 14, 6], "view": [6], "available": [14, 11, 7], "requirement": [14, 7], "notational": [16], "configured": [1], "humans": [13], "module": [3, 2, 7, 6], "distantly": [9], "computer": [2], "enhanced": [7], "btn": [11], "machinesetup": [11], "interacting": [4], "written": [6, 1, 4, 14], "routine": [5], "progress": [2], "flickr": [1], "youll": [2, 7], "email": [13, 1, 14], "interchangeably": [7], "agencies": [9], "historians": [5], "synced": [1], "disconnect": [4], "impairments": [6], "optional": [13], "paraphrasing": [6], "instant": [9], "plugin": [13], "goal": [5], "april": [14, 6], "admit": [9], "grain": [5], "attributes": [7], "jumbotron": [11], "grounds": [2], "detailed": [2, 6, 7], "relevant": [9], "author": [7], "interface": [1], "crafted": [2], "respect": [4, 6], "undergraduate": [14], "platform": [2], "discrimination": [6], "define": [9], "username": [4], "diversity": [6], "graphics": [7], "quotation": [6], "wood": [5], "plain": [1], "align": [5], "appearance": [4], "value": [2, 6], "will": [2, 7, 9, 13, 5, 14, 1, 4, 11], "carleton": [11, 14, 6, 1, 2, 13], "capta": [7], "thus": [9], "site": [1, 2, 7], "encouragement": [4], "helped": [2], "admgen4": [14], "examined": [5, 6], "sits": [5], "perhaps": [2], "member": [6], "parts": [2, 7], "shawngraham": [1, 2, 12, 13, 11], "gets": [12], "attribution-noncommercial-sharealike": [6], "spell": [4], "http": [7, 2, 1, 13, 14, 6, 12, 4, 11], "upon": [2, 6], "effect": [1, 7], "proficiency": [14], "student": [14, 6, 7], "frequently": [1], "identity": [9, 12, 5], "off": [7], "reflection": [9], "colour": [7], "well": [7, 1, 13], "thought": [2, 7], "patterns": [9, 4, 5], "command": [1], "english": [14], "latest": [5], "less": [5], "moments": [5], "executive": [13], "obtain": [6], "sources": [2, 7, 9, 6], "paul": [6, 7], "begin": [13], "web": [2], "generous": [4], "residential": [7], "large-scale": [9], "realize": [7], "book": [11], "attractive": [7], "infographics": [9], "smart": [4], "resolved": [6], "tests": [9], "fyi": [2], "five": [2, 7], "whatever": [1, 9, 7], "helpful": [4, 7], "lost": [2, 7], "sizes": [5], "admitted": [14], "become": [1, 9, 7], "works": [2, 4, 6], "page": [12, 9, 2, 14, 7], "because": [6, 14, 4, 13], "twitter": [13, 1, 12], "searching": [7], "library": [13], "gradebook": [7], "platforms": [9], "growth": [6], "proper": [6, 12], "home": [12, 6], "happens": [5], "lead": [7], "avoid": [4], "computer-based": [2], "sketching": [7], "rewarding": [9], "does": [7, 5], "assuming": [4], "non-degree-students": [14], "regain": [5], "omeka": [2], "journal": [7], "host": [13], "openaccess": [11], "analyses": [7], "stage": [5], "about": [1, 2, 7, 9, 5, 4, 14], "actual": [13, 7], "getting": [9], "freedom": [6], "recognized": [7], "pysical": [4], "eligibility": [14], "software": [13, 11], "own": [5, 2, 13, 6, 1, 4, 7, 9], "redditdata": [7], "year": [13], "labbook": [2], "dataset": [7], "assess": [2], "chronic": [6], "doesnt": [7, 2, 13, 4, 5], "registration": [14], "van": [1], "additional": [14], "inspiration": [5, 1, 7], "function": [7], "560": [9, 1, 7, 10, 16, 17], "thenounproject": [1], "expected": [2], "duedates": [9], "made": [2], "whether": [2, 4, 6], "wish": [4, 7], "official": [14, 13, 6], "hosting": [10, 13], "record": [5], "below": [1, 2, 12, 6], "convince": [7], "iterated": [4], "reclaimhosting": [13], "demonstrate": [7], "problem": [2, 13, 7], "piece": [2, 5, 6, 7, 4], "recognize": [2], "contribute": [9], "campus": [2, 14], "mutual": [4], "offensive": [4], "detail": [2, 5], "scholarly": [9, 6], "lately": [5], "other": [2, 4, 5, 7, 1, 6, 14, 9, 13], "details": [14, 2, 11], "branch": [1], "welcomes": [11], "contacting": [9], "convicts": [7], "kinds": [7], "stay": [1], "chance": [1], "finally-": [7], "exposure": [5], "starting": [7], "blogs": [1], "intentionally": [6], "status": [14]}, "updated": 1450188274, "ids": {"1": "about.html", "2": "assessment.html", "3": "canadianaapi.html", "4": "codeofconduct.html", "5": "crafting.html", "6": "duedates.html", "7": "finalproject.html", "8": "forking.html", "9": "getting-started.html", "10": "hostinghtmlgithub.html", "11": "index.html", "12": "landingpageingithub.html", "13": "machinesetup.html", "14": "openaccess.html", "15": "questionnaire.html", "16": "settingupopennotebook.html", "17": "videointro.html"}, "tags": {"essay": [5], "getting started": [9, 12, 13, 15], "final project": [2, 7, 17], "github": [8, 10, 12], "paradata": [2], "registration": [14], "modules": [2, 16], "due dates": [6], "syllabus": [6, 17], "module 2": [3], "notebook": [16], "video": [3, 8, 10, 12, 16, 17], "open access": [14], "conduct": [4], "workbook": [16, 17], "assessment": [2, 6, 7, 17], "setup": [9, 12, 13, 15], "participation": [14], "instructions": [6]}}